sledge/__init__.py
sledge-0.1.4.dist-info/LICENSE
sledge-0.1.4.dist-info/METADATA
sledge-0.1.4.dist-info/WHEEL
sledge-0.1.4.dist-info/top_level.txt
sledge-0.1.4.dist-info/RECORD
