Metadata-Version: 2.1
Name: sledge
Version: 0.1.4
Summary: SLEDge: semantic evaluation of clustering results
Home-page: https://verri.github.io/sledge
Author: Douglas Aquino, Filipe Verri
Author-email: douglasaquino.ee@gmail.com, filipeverri@gmail.com
License: UNKNOWN
Project-URL: Bug Tracker, https://github.com/verri/sledge/issues
Platform: UNKNOWN
Classifier: Programming Language :: Python :: 3
Classifier: License :: OSI Approved :: MIT License
Classifier: Operating System :: OS Independent
Requires-Python: >=3.6
License-File: LICENSE
Requires-Dist: pandas
Requires-Dist: numpy
